molo.commenting-11.2.1-py3.8-nspkg.pth
molo/commenting/__init__.py
molo/commenting/admin.py
molo/commenting/admin_import_export.py
molo/commenting/admin_views.py
molo/commenting/forms.py
molo/commenting/managers.py
molo/commenting/models.py
molo/commenting/rules.py
molo/commenting/tasks.py
molo/commenting/urls.py
molo/commenting/views.py
molo/commenting/wagtail_hooks.py
molo/commenting/migrations/0001_initial.py
molo/commenting/migrations/0002_auto_20151105_1214.py
molo/commenting/migrations/0003_cannedresponse.py
molo/commenting/migrations/0004_auto_20160713_0221.py
molo/commenting/migrations/0005_add_commenting_permissions_to_groups.py
molo/commenting/migrations/0006_add_wagtail_site_to_comment.py
molo/commenting/migrations/0007_add_current_site_to_all_comments.py
molo/commenting/migrations/0008_commentdatarule.py
molo/commenting/migrations/__init__.py
molo/commenting/templates/admin/moderate.html
molo/commenting/templates/admin/molo_comments_admin.html
molo/commenting/templates/admin/molo_comments_admin_reply.html
molo/commenting/templates/admin/molo_comments_date_range_filter.html
molo/commenting/templates/admin/reply.html
molo/commenting/templates/comments/comment.html
molo/commenting/templates/comments/comment_block.html
molo/commenting/templates/comments/comment_done.html
molo/commenting/templates/comments/comments.html
molo/commenting/templates/comments/form.html
molo/commenting/templates/comments/preview.html
molo/commenting/templates/comments/reply.html
molo/commenting/templates/comments/report_response.html
molo/commenting/templates/notifications/notice.html
molo/commenting/templates/notifications/reply_list.html
molo/commenting/templates/notifications/tags/notification_banner.html
molo/commenting/templatetags/__init__.py
molo/commenting/templatetags/molo_commenting_tags.py
molo/commenting/test_templates/article_page.html
molo/commenting/test_templates/main.html
molo/commenting/tests/__init__.py
molo/commenting/tests/test_admin.py
molo.commenting-11.2.1.dist-info/LICENSE
molo.commenting-11.2.1.dist-info/METADATA
molo.commenting-11.2.1.dist-info/WHEEL
molo.commenting-11.2.1.dist-info/namespace_packages.txt
molo.commenting-11.2.1.dist-info/top_level.txt
molo.commenting-11.2.1.dist-info/RECORD
