Metadata-Version: 2.1
Name: molo.commenting
Version: 11.2.1
Summary: Comments helpers for sites built with Molo.
Home-page: http://github.com/praekelt/molo.commenting
Author: Praekelt Foundation
Author-email: dev@praekelt.com
License: BSD
Keywords: praekelt,mobi,web,django
Platform: UNKNOWN
Classifier: Programming Language :: Python
Classifier: Framework :: Django
Classifier: Topic :: Internet :: WWW/HTTP
Classifier: Topic :: Internet :: WWW/HTTP :: WSGI :: Application
License-File: LICENSE
Requires-Dist: molo.core (<12.0.0,>=11.0.5)
Requires-Dist: django-contrib-comments (==2.0.0)
Requires-Dist: django-import-export
Requires-Dist: django-notifications-hq
Requires-Dist: wagtail-personalisation-molo (<4.0.0,>=3.0.4)
Requires-Dist: Unidecode (==0.04.16)
Requires-Dist: django-admin-rangefilter (==0.8.1)
